flood_forecast/evaluator.py
flood_forecast/explain_model_output.py
flood_forecast/long_train.py
flood_forecast/meta_train.py
flood_forecast/model_dict_function.py
flood_forecast/plot_functions.py
flood_forecast/pre_dict.py
flood_forecast/pytorch_training.py
flood_forecast/series_id_helper.py
flood_forecast/temporal_decoding.py
flood_forecast/time_model.py
flood_forecast/trainer.py
flood_forecast/training_utils.py
flood_forecast/utils.py
flood_forecast/basic/base_line_methods.py
flood_forecast/basic/d_n_linear.py
flood_forecast/basic/gru_vanilla.py
flood_forecast/basic/linear_regression.py
flood_forecast/basic/lstm_vanilla.py
flood_forecast/custom/custom_activation.py
flood_forecast/custom/custom_opt.py
flood_forecast/custom/dilate_loss.py
flood_forecast/custom/focal_loss.py
flood_forecast/da_rnn/constants.py
flood_forecast/da_rnn/custom_types.py
flood_forecast/da_rnn/main_predict.py
flood_forecast/da_rnn/model.py
flood_forecast/da_rnn/modules.py
flood_forecast/da_rnn/train_da.py
flood_forecast/da_rnn/utils.py
flood_forecast/deployment/inference.py
flood_forecast/gcp_integration/basic_utils.py
flood_forecast/meta_models/basic_ae.py
flood_forecast/meta_models/merging_model.py
flood_forecast/preprocessing/buil_dataset.py
flood_forecast/preprocessing/closest_station.py
flood_forecast/preprocessing/data_converter.py
flood_forecast/preprocessing/eco_gage_set.py
flood_forecast/preprocessing/interpolate_preprocess.py
flood_forecast/preprocessing/preprocess_da_rnn.py
flood_forecast/preprocessing/preprocess_metadata.py
flood_forecast/preprocessing/process_usgs.py
flood_forecast/preprocessing/pytorch_loaders.py
flood_forecast/preprocessing/temporal_feats.py
flood_forecast/transformer_xl/attn.py
flood_forecast/transformer_xl/basis_former.py
flood_forecast/transformer_xl/cross_former.py
flood_forecast/transformer_xl/data_embedding.py
flood_forecast/transformer_xl/dsanet.py
flood_forecast/transformer_xl/dummy_torch.py
flood_forecast/transformer_xl/informer.py
flood_forecast-1.0.dev0.dist-info/LICENSE
flood_forecast-1.0.dev0.dist-info/METADATA
flood_forecast-1.0.dev0.dist-info/WHEEL
flood_forecast-1.0.dev0.dist-info/top_level.txt
flood_forecast-1.0.dev0.dist-info/RECORD
